msgpack_serializer/__init__.py
msgpack_serializer/serializer.py
django_msgpack_serializer-1.0.0.dist-info/METADATA
django_msgpack_serializer-1.0.0.dist-info/WHEEL
django_msgpack_serializer-1.0.0.dist-info/LICENSE
django_msgpack_serializer-1.0.0.dist-info/RECORD
