Metadata-Version: 2.1
Name: django-msgpack-serializer
Version: 1.0.0
Summary: A MsgPack serializer for Django.
Home-page: https://github.com/fcurella/django-msgpack-serializer
License: MIT
Author: Flavio Curella
Author-email: flavio.curella@gmail.com
Requires-Python: >=3.8.1,<4.0.0
Classifier: Development Status :: 3 - Alpha
Classifier: Environment :: Console
Classifier: Framework :: Django
Classifier: Intended Audience :: Developers
Classifier: Intended Audience :: Information Technology
Classifier: License :: OSI Approved :: MIT License
Classifier: Operating System :: OS Independent
Classifier: Programming Language :: Python :: 3
Classifier: Programming Language :: Python :: 3.9
Classifier: Programming Language :: Python :: 3.10
Classifier: Programming Language :: Python :: 3.11
Requires-Dist: django (>=3.2,<5)
Requires-Dist: msgpack (>=1.0.4,<2.0.0)
Project-URL: Repository, https://github.com/fcurella/django-msgpack-serializer
